setup.cfg
setup.py
mongo_cache/__init__.py
mongo_cache/mongo_cache.py
mongo_cache.egg-info/PKG-INFO
mongo_cache.egg-info/SOURCES.txt
mongo_cache.egg-info/dependency_links.txt
mongo_cache.egg-info/requires.txt
mongo_cache.egg-info/top_level.txt
test/test_mongo_cache.py