Metadata-Version: 1.1
Name: mongo-cache
Version: 0.1.1
Summary: A library for a cache backed by mongodb
Home-page: https://github.com/ktaragorn/mongo_cache
Author: Karthik T
Author-email: karthikt.holmes+github@gmail.com
License: UNKNOWN
Download-URL: https://github.com/ktaragorn/mongo_cache/tarball/0.1.1
Keywords: cache,mongodb
Platform: UNKNOWN
